kay/__init__.py
kay/helpers/api.py
kay/helpers/exceptions.py
kay/rag/retrievers.py
kay-0.1.0.dist-info/LICENSE
kay-0.1.0.dist-info/METADATA
kay-0.1.0.dist-info/WHEEL
kay-0.1.0.dist-info/top_level.txt
kay-0.1.0.dist-info/RECORD
