Metadata-Version: 2.1
Name: kay
Version: 0.1.0
Summary: Data API for Context Retrieval
License: MIT License
Requires-Python: <4.0,>=3.8.1
License-File: LICENSE
Requires-Dist: requests >=2
